Metadata-Version: 1.0
Name: self-practice-probability
Version: 1.3
Summary: Gaussian and Binomial distributions
Home-page: UNKNOWN
Author: Shamushideen Sule
Author-email: aneru.sule@gmail.com
License: UNKNOWN
Platform: UNKNOWN
